mediaApiClient/__init__.py
mediaApiClient/account_models.py
mediaApiClient/client_account_controller_v1.py
mediaApiClient/client_compilation_controller_v2.py
mediaApiClient/client_content_controller_v2.py
mediaApiClient/client_service_controller_v1.py
mediaApiClient/client_stream_controller_v2.py
mediaApiClient/compilation_models.py
mediaApiClient/content_meta_models.py
mediaApiClient/content_reuest_models.py
mediaApiClient/services_models.py
mediaApiClient/stream_models.py
mediaApiClient/test.py
mediaApiClient-1.0.8.dist-info/LICENSE
mediaApiClient-1.0.8.dist-info/METADATA
mediaApiClient-1.0.8.dist-info/WHEEL
mediaApiClient-1.0.8.dist-info/top_level.txt
mediaApiClient-1.0.8.dist-info/RECORD
