Metadata-Version: 2.1
Name: mediaApiClient
Version: 1.0.8
Summary: A library for working with REST API of CAG
Home-page: https://dev.mediatech.by/mediapi-public/mediaapiclient_python
Author: Semyon Shilovskiy
Author-email: opensource@mediatech.dev
License: BSD 3-Clause License
License-File: LICENSE
Requires-Dist: pydantic (~=2.2.1)
Requires-Dist: setuptools (~=65.5.1)
Requires-Dist: requests (~=2.31.0)
